twilight_utils/__init__.py
twilight_utils/py.typed
twilight_utils/more_str/__init__.py
twilight_utils/more_str/generators.py
twilight_utils/more_typing/__init__.py
twilight_utils/more_typing/signatures.py
twilight_utils/more_typing/undefined.py
twilight_utils-0.0.1.dist-info/METADATA
twilight_utils-0.0.1.dist-info/WHEEL
twilight_utils-0.0.1.dist-info/licenses/LICENSE
twilight_utils-0.0.1.dist-info/RECORD
