Metadata-Version: 2.3
Name: twilight-utils
Version: 0.0.1
Summary: Library of python utility functions you copy in every damn project
Project-URL: Homepage, https://github.com/TwilightWeave/TwilightUtils
Project-URL: Repository, https://github.com/TwilightWeave/TwilightUtils
Project-URL: IssueTracker, https://github.com/TwilightWeave/TwilightUtils/issues
Author-email: Jaden Corr <jaden.corr88@gmail.com>
License: BSD-3-Clause
Keywords: python utilities,utilities
Classifier: Development Status :: 5 - Production/Stable
Classifier: Intended Audience :: Developers
Classifier: License :: OSI Approved :: BSD License
Classifier: Programming Language :: Python :: 3
Classifier: Programming Language :: Python :: 3.13
Requires-Python: >=3.13
